Workbook

Sheet Como usar
A1: Como usar a calculadora
A3: 1. Na folha 'Precos', para cada produto escreve nas células AMARELAS:
A4: • Custo no fornecedor (€): o preço a que compras no site do fornecedor.
A5: • Concorrente mais barato no Google (€): o preço mais baixo que encontras em sites portugueses.
A6: • Link do concorrente: para voltares a verificar mais tarde.
A7: 2. A coluna 'Preço sugerido' diz-te o preço a pôr na loja (termina sempre em ,99).
A8: 3. A coluna 'Estado' diz se consegues competir:
A9: • Competitivo: ficas abaixo do concorrente e ganhas pelo menos a margem mínima.
A10: • Pouco competitivo: para ganhares a margem mínima tens de ser mais caro que o concorrente. Pensa se vale a pena vender.
A11: • Sem concorrente: usa o preço mínimo (ou procura melhor no Google).
A12: 4. Copia o preço sugerido para a coluna 'preco' do Catalogo.xlsx (ou para o admin da loja).
A14: Regra usada:
... A19: Células amarelas com texto azul = valores que tu preenches. Texto preto = fórmulas, não mexer.

Sheet Parametros
A1: Parâmetros da loja
A3: Parâmetro | B3: Valor | C3: Nota
A4: Portes por encomenda (€) | B4: 3.75 | C4: Valor dado pela Inês (custo de envio do fornecedor).
A5: Margem mínima sobre o custo (%) | B5: 0.1 | C5: Valor dado pela Inês: 10% sobre o custo total (produto + portes).
A6: Ficar abaixo do concorrente (%) | B6: 0.03 | C6: Pressuposto do Claude: ficar 3% abaixo do mais barato no Google. Ajusta à vontade.
A7: Comissão de pagamento (%) | B7: 0 | C7: A CONFIRMAR: comissão percentual da Ifthenpay (Multibanco/MB WAY). Vê no teu contrato.
A8: Comissão de pagamento fixa (€) | B8: 0 | C8: A CONFIRMAR: valor fixo por transação da Ifthenpay, se existir.
A9: IVA a acrescentar ao preço (%) | B9: 0 | C9: A CONFIRMAR: 0% se estás isenta de IVA (art. 53.º, regime de isenção); 23% se cobras IVA. Se o custo do fornecedor já inclui IVA e não o recuperas, deixa 0%.

Sheet Precos
A1: Calculadora de preços — New Recycled
A2: Preenche só as células amarelas (custo, concorrente, link). Tudo o resto é calculado. Parâmetros na folha 'Parametros'.
A4: Produto | B4: Referência | C4: Preço atual na loja (€) | D4: Custo no fornecedor (€) | E4: Concorrente mais barato no Google (€) | F4: Link do concorrente | G4: Custo total c/ portes (€) | H4: Preço mínimo (€) | I4: Preço sugerido (€) | J4: Lucro por venda (€) | K4: Margem real s/ custo (%) | L4: Estado
A5: EXEMPLO (apagar depois) | B5: XXX | D5: 6.5 | E5: 14.9 | F5: https://exemplo.pt/produto | G5: =IF(D5="","",D5+Parametros!$B$4) -> 10.25 | H5: =IF(D5="","",(G5*(1+Parametros!$B$5)+Parametros!$B$8)/(1-Parametros!$B$7)*(1+Parametros!$B$9)) -> 11.275 | I5: =IF(D5="","",IF(E5="",(CEILING(H5+0.01,1)-0.01),MAX((CEILING(H5+0.01,1)-0.01),(FLOOR(E5*(1-Parametros!$B$6)+0.01,1)-0.01)))) -> 13.99 | J5: =IF(I5="","",I5/(1+Parametros!$B$9)-I5*Parametros!$B$7-Parametros!$B$8-G5) -> 3.74 | K5: =IF(J5="","",IF(G5=0,"",J5/G5)) -> 0.36487805 | L5: =IF(AND(A5="",D5=""),"",IF(D5="","Preencher custo",IF(E5="","Sem concorrente",IF((FLOOR(E5*(1-Parametros!$B$6)+0.01,1)-0.01)>=(CEILING(H5+0.01,1)-0.01),"Competitivo","Pouco competitivo")))) -> Competitivo
A6: Toner Brother TN1050 Compatível | B6: TN1050 | C6: 12.99 | G6: =IF(D6="","",D6+Parametros!$B$4) | H6: =IF(D6="","",(G6*(1+Parametros!$B$5)+Parametros!$B$8)/(1-Parametros!$B$7)*(1+Parametros!$B$9)) | I6: =IF(D6="","",IF(E6="",(CEILING(H6+0.01,1)-0.01),MAX((CEILING(H6+0.01,1)-0.01),(FLOOR(E6*(1-Parametros!$B$6)+0.01,1)-0.01)))) | J6: =IF(I6="","",I6/(1+Parametros!$B$9)-I6*Parametros!$B$7-Parametros!$B$8-G6) | K6: =IF(J6="","",IF(G6=0,"",J6/G6)) | L6: =IF(AND(A6="",D6=""),"",IF(D6="","Preencher custo",IF(E6="","Sem concorrente",IF((FLOOR(E6*(1-Parametros!$B$6)+0.01,1)-0.01)>=(CEILING(H6+0.01,1)-0.01),"Competitivo","Pouco competitivo")))) -> Preencher custo
A7: Pack HP 603XL Compatível | B7: 603XL | C7: 19.99 | G7: =IF(D7="","",D7+Parametros!$B$4) | H7: =IF(D7="","",(G7*(1+Parametros!$B$5)+Parametros!$B$8)/(1-Parametros!$B$7)*(1+Parametros!$B$9)) | I7: =IF(D7="","",IF(E7="",(CEILING(H7+0.01,1)-0.01),MAX((CEILING(H7+0.01,1)-0.01),(FLOOR(E7*(1-Parametros!$B$6)+0.01,1)-0.01)))) | J7: =IF(I7="","",I7/(1+Parametros!$B$9)-I7*Parametros!$B$7-Parametros!$B$8-G7) | K7: =IF(J7="","",IF(G7=0,"",J7/G7)) | L7: =IF(AND(A7="",D7=""),"",IF(D7="","Preencher custo",IF(E7="","Sem concorrente",IF((FLOOR(E7*(1-Parametros!$B$6)+0.01,1)-0.01)>=(CEILING(H7+0.01,1)-0.01),"Competitivo","Pouco competitivo")))) -> Preencher custo
A8: Rolo Térmico 57x35x11 | B8: 57x35x11 | G8: =IF(D8="","",D8+Parametros!$B$4) | H8: =IF(D8="","",(G8*(1+Parametros!$B$5)+Parametros!$B$8)/(1-Parametros!$B$7)*(1+Parametros!$B$9)) | I8: =IF(D8="","",IF(E8="",(CEILING(H8+0.01,1)-0.01),MAX((CEILING(H8+0.01,1)-0.01),(FLOOR(E8*(1-Parametros!$B$6)+0.01,1)-0.01)))) | J8: =IF(I8="","",I8/(1+Parametros!$B$9)-I8*Parametros!$B$7-Parametros!$B$8-G8) | K8: =IF(J8="","",IF(G8=0,"",J8/G8)) | L8: =IF(AND(A8="",D8=""),"",IF(D8="","Preencher custo",IF(E8="","Sem concorrente",IF((FLOOR(E8*(1-Parametros!$B$6)+0.01,1)-0.01)>=(CEILING(H8+0.01,1)-0.01),"Competitivo","Pouco competitivo")))) -> Preencher custo
A9: Papel A4 80g - Resma | B9: A4 80g | G9: =IF(D9="","",D9+Parametros!$B$4) | H9: =IF(D9="","",(G9*(1+Parametros!$B$5)+Parametros!$B$8)/(1-Parametros!$B$7)*(1+Parametros!$B$9)) | I9: =IF(D9="","",IF(E9="",(CEILING(H9+0.01,1)-0.01),MAX((CEILING(H9+0.01,1)-0.01),(FLOOR(E9*(1-Parametros!$B$6)+0.01,1)-0.01)))) | J9: =IF(I9="","",I9/(1+Parametros!$B$9)-I9*Parametros!$B$7-Parametros!$B$8-G9) | K9: =IF(J9="","",IF(G9=0,"",J9/G9)) | L9: =IF(AND(A9="",D9=""),"",IF(D9="","Preencher custo",IF(E9="","Sem concorrente",IF((FLOOR(E9*(1-Parametros!$B$6)+0.01,1)-0.01)>=(CEILING(H9+0.01,1)-0.01),"Competitivo","Pouco competitivo")))) -> Preencher custo
G10: =IF(D10="","",D10+Parametros!$B$4) | H10: =IF(D10="","",(G10*(1+Parametros!$B$5)+Parametros!$B$8)/(1-Parametros!$B$7)*(1+Parametros!$B$9)) | I10: =IF(D10="","",IF(E10="",(CEILING(H10+0.01,1)-0.01),MAX((CEILING(H10+0.01,1)-0.01),(FLOOR(E10*(1-Parametros!$B$6)+0.01,1)-0.01)))) | J10: =IF(I10="","",I10/(1+Parametros!$B$9)-I10*Parametros!$B$7-Parametros!$B$8-G10) | K10: =IF(J10="","",IF(G10=0,"",J10/G10)) | L10: =IF(AND(A10="",D10=""),"",IF(D10="","Preencher custo",IF(E10="","Sem concorrente",IF((FLOOR(E10*(1-Parametros!$B$6)+0.01,1)-0.01)>=(CEILING(H10+0.01,1)-0.01),"Competitivo","Pouco competitivo"))))
G11: =IF(D11="","",D11+Parametros!$B$4) | H11: =IF(D11="","",(G11*(1+Parametros!$B$5)+Parametros!$B$8)/(1-Parametros!$B$7)*(1+Parametros!$B$9)) | I11: =IF(D11="","",IF(E11="",(CEILING(H11+0.01,1)-0.01),MAX((CEILING(H11+0.01,1)-0.01),(FLOOR(E11*(1-Parametros!$B$6)+0.01,1)-0.01)))) | J11: =IF(I11="","",I11/(1+Parametros!$B$9)-I11*Parametros!$B$7-Parametros!$B$8-G11) | K11: =IF(J11="","",IF(G11=0,"",J11/G11)) | L11: =IF(AND(A11="",D11=""),"",IF(D11="","Preencher custo",IF(E11="","Sem concorrente",IF((FLOOR(E11*(1-Parametros!$B$6)+0.01,1)-0.01)>=(CEILING(H11+0.01,1)-0.01),"Competitivo","Pouco competitivo"))))
G12: =IF(D12="","",D12+Parametros!$B$4) | H12: =IF(D12="","",(G12*(1+Parametros!$B$5)+Parametros!$B$8)/(1-Parametros!$B$7)*(1+Parametros!$B$9)) | I12: =IF(D12="","",IF(E12="",(CEILING(H12+0.01,1)-0.01),MAX((CEILING(H12+0.01,1)-0.01),(FLOOR(E12*(1-Parametros!$B$6)+0.01,1)-0.01)))) | J12: =IF(I12="","",I12/(1+Parametros!$B$9)-I12*Parametros!$B$7-Parametros!$B$8-G12) | K12: =IF(J12="","",IF(G12=0,"",J12/G12)) | L12: =IF(AND(A12="",D12=""),"",IF(D12="","Preencher custo",IF(E12="","Sem concorrente",IF((FLOOR(E12*(1-Parametros!$B$6)+0.01,1)-0.01)>=(CEILING(H12+0.01,1)-0.01),"Competitivo","Pouco competitivo"))))
G13: =IF(D13="","",D13+Parametros!$B$4) | H13: =IF(D13="","",(G13*(1+Parametros!$B$5)+Parametros!$B$8)/(1-Parametros!$B$7)*(1+Parametros!$B$9)) | I13: =IF(D13="","",IF(E13="",(CEILING(H13+0.01,1)-0.01),MAX((CEILING(H13+0.01,1)-0.01),(FLOOR(E13*(1-Parametros!$B$6)+0.01,1)-0.01)))) | J13: =IF(I13="","",I13/(1+Parametros!$B$9)-I13*Parametros!$B$7-Parametros!$B$8-G13) | K13: =IF(J13="","",IF(G13=0,"",J13/G13)) | L13: =IF(AND(A13="",D13=""),"",IF(D13="","Preencher custo",IF(E13="","Sem concorrente",IF((FLOOR(E13*(1-Parametros!$B$6)+0.01,1)-0.01)>=(CEILING(H13+0.01,1)-0.01),"Competitivo","Pouco competitivo"))))
G14: =IF(D14="","",D14+Parametros!$B$4) | H14: =IF(D14="","",(G14*(1+Parametros!$B$5)+Parametros!$B$8)/(1-Parametros!$B$7)*(1+Parametros!$B$9)) | I14: =IF(D14="","",IF(E14="",(CEILING(H14+0.01,1)-0.01),MAX((CEILING(H14+0.01,1)-0.01),(FLOOR(E14*(1-Parametros!$B$6)+0.01,1)-0.01)))) | J14: =IF(I14="","",I14/(1+Parametros!$B$9)-I14*Parametros!$B$7-Parametros!$B$8-G14) | K14: =IF(J14="","",IF(G14=0,"",J14/G14)) | L14: =IF(AND(A14="",D14=""),"",IF(D14="","Preencher custo",IF(E14="","Sem concorrente",IF((FLOOR(E14*(1-Parametros!$B$6)+0.01,1)-0.01)>=(CEILING(H14+0.01,1)-0.01),"Competitivo","Pouco competitivo"))))
G15: =IF(D15="","",D15+Parametros!$B$4) | H15: =IF(D15="","",(G15*(1+Parametros!$B$5)+Parametros!$B$8)/(1-Parametros!$B$7)*(1+Parametros!$B$9)) | I15: =IF(D15="","",IF(E15="",(CEILING(H15+0.01,1)-0.01),MAX((CEILING(H15+0.01,1)-0.01),(FLOOR(E15*(1-Parametros!$B$6)+0.01,1)-0.01)))) | J15: =IF(I15="","",I15/(1+Parametros!$B$9)-I15*Parametros!$B$7-Parametros!$B$8-G15) | K15: =IF(J15="","",IF(G15=0,"",J15/G15)) | L15: =IF(AND(A15="",D15=""),"",IF(D15="","Preencher custo",IF(E15="","Sem concorrente",IF((FLOOR(E15*(1-Parametros!$B$6)+0.01,1)-0.01)>=(CEILING(H15+0.01,1)-0.01),"Competitivo","Pouco competitivo"))))
G16: =IF(D16="","",D16+Parametros!$B$4) | H16: =IF(D16="","",(G16*(1+Parametros!$B$5)+Parametros!$B$8)/(1-Parametros!$B$7)*(1+Parametros!$B$9)) | I16: =IF(D16="","",IF(E16="",(CEILING(H16+0.01,1)-0.01),MAX((CEILING(H16+0.01,1)-0.01),(FLOOR(E16*(1-Parametros!$B$6)+0.01,1)-0.01)))) | J16: =IF(I16="","",I16/(1+Parametros!$B$9)-I16*Parametros!$B$7-Parametros!$B$8-G16) | K16: =IF(J16="","",IF(G16=0,"",J16/G16)) | L16: =IF(AND(A16="",D16=""),"",IF(D16="","Preencher custo",IF(E16="","Sem concorrente",IF((FLOOR(E16*(1-Parametros!$B$6)+0.01,1)-0.01)>=(CEILING(H16+0.01,1)-0.01),"Competitivo","Pouco competitivo"))))
G17: =IF(D17="","",D17+Parametros!$B$4) | H17: =IF(D17="","",(G17*(1+Parametros!$B$5)+Parametros!$B$8)/(1-Parametros!$B$7)*(1+Parametros!$B$9)) | I17: =IF(D17="","",IF(E17="",(CEILING(H17+0.01,1)-0.01),MAX((CEILING(H17+0.01,1)-0.01),(FLOOR(E17*(1-Parametros!$B$6)+0.01,1)-0.01)))) | J17: =IF(I17="","",I17/(1+Parametros!$B$9)-I17*Parametros!$B$7-Parametros!$B$8-G17) | K17: =IF(J17="","",IF(G17=0,"",J17/G17)) | L17: =IF(AND(A17="",D17=""),"",IF(D17="","Preencher custo",IF(E17="","Sem concorrente",IF((FLOOR(E17*(1-Parametros!$B$6)+0.01,1)-0.01)>=(CEILING(H17+0.01,1)-0.01),"Competitivo","Pouco competitivo"))))
G18: =IF(D18="","",D18+Parametros!$B$4) | H18: =IF(D18="","",(G18*(1+Parametros!$B$5)+Parametros!$B$8)/(1-Parametros!$B$7)*(1+Parametros!$B$9)) | I18: =IF(D18="","",IF(E18="",(CEILING(H18+0.01,1)-0.01),MAX((CEILING(H18+0.01,1)-0.01),(FLOOR(E18*(1-Parametros!$B$6)+0.01,1)-0.01)))) | J18: =IF(I18="","",I18/(1+Parametros!$B$9)-I18*Parametros!$B$7-Parametros!$B$8-G18) | K18: =IF(J18="","",IF(G18=0,"",J18/G18)) | L18: =IF(AND(A18="",D18=""),"",IF(D18="","Preencher custo",IF(E18="","Sem concorrente",IF((FLOOR(E18*(1-Parametros!$B$6)+0.01,1)-0.01)>=(CEILING(H18+0.01,1)-0.01),"Competitivo","Pouco competitivo"))))
G19: =IF(D19="","",D19+Parametros!$B$4) | H19: =IF(D19="","",(G19*(1+Parametros!$B$5)+Parametros!$B$8)/(1-Parametros!$B$7)*(1+Parametros!$B$9)) | I19: =IF(D19="","",IF(E19="",(CEILING(H19+0.01,1)-0.01),MAX((CEILING(H19+0.01,1)-0.01),(FLOOR(E19*(1-Parametros!$B$6)+0.01,1)-0.01)))) | J19: =IF(I19="","",I19/(1+Parametros!$B$9)-I19*Parametros!$B$7-Parametros!$B$8-G19) | K19: =IF(J19="","",IF(G19=0,"",J19/G19)) | L19: =IF(AND(A19="",D19=""),"",IF(D19="","Preencher custo",IF(E19="","Sem concorrente",IF((FLOOR(E19*(1-Parametros!$B$6)+0.01,1)-0.01)>=(CEILING(H19+0.01,1)-0.01),"Competitivo","Pouco competitivo"))))
G20: =IF(D20="","",D20+Parametros!$B$4) | H20: =IF(D20="","",(G20*(1+Parametros!$B$5)+Parametros!$B$8)/(1-Parametros!$B$7)*(1+Parametros!$B$9)) | I20: =IF(D20="","",IF(E20="",(CEILING(H20+0.01,1)-0.01),MAX((CEILING(H20+0.01,1)-0.01),(FLOOR(E20*(1-Parametros!$B$6)+0.01,1)-0.01)))) | J20: =IF(I20="","",I20/(1+Parametros!$B$9)-I20*Parametros!$B$7-Parametros!$B$8-G20) | K20: =IF(J20="","",IF(G20=0,"",J20/G20)) | L20: =IF(AND(A20="",D20=""),"",IF(D20="","Preencher custo",IF(E20="","Sem concorrente",IF((FLOOR(E20*(1-Parametros!$B$6)+0.01,1)-0.01)>=(CEILING(H20+0.01,1)-0.01),"Competitivo","Pouco competitivo"))))
G21: =IF(D21="","",D21+Parametros!$B$4) | H21: =IF(D21="","",(G21*(1+Parametros!$B$5)+Parametros!$B$8)/(1-Parametros!$B$7)*(1+Parametros!$B$9)) | I21: =IF(D21="","",IF(E21="",(CEILING(H21+0.01,1)-0.01),MAX((CEILING(H21+0.01,1)-0.01),(FLOOR(E21*(1-Parametros!$B$6)+0.01,1)-0.01)))) | J21: =IF(I21="","",I21/(1+Parametros!$B$9)-I21*Parametros!$B$7-Parametros!$B$8-G21) | K21: =IF(J21="","",IF(G21=0,"",J21/G21)) | L21: =IF(AND(A21="",D21=""),"",IF(D21="","Preencher custo",IF(E21="","Sem concorrente",IF((FLOOR(E21*(1-Parametros!$B$6)+0.01,1)-0.01)>=(CEILING(H21+0.01,1)-0.01),"Competitivo","Pouco competitivo"))))
... G54: =IF(D54="","",D54+Parametros!$B$4) | H54: =IF(D54="","",(G54*(1+Parametros!$B$5)+Parametros!$B$8)/(1-Parametros!$B$7)*(1+Parametros!$B$9)) | I54: =IF(D54="","",IF(E54="",(CEILING(H54+0.01,1)-0.01),MAX((CEILING(H54+0.01,1)-0.01),(FLOOR(E54*(1-Parametros!$B$6)+0.01,1)-0.01)))) | J54: =IF(I54="","",I54/(1+Parametros!$B$9)-I54*Parametros!$B$7-Parametros!$B$8-G54) | K54: =IF(J54="","",IF(G54=0,"",J54/G54)) | L54: =IF(AND(A54="",D54=""),"",IF(D54="","Preencher custo",IF(E54="","Sem concorrente",IF((FLOOR(E54*(1-Parametros!$B$6)+0.01,1)-0.01)>=(CEILING(H54+0.01,1)-0.01),"Competitivo","Pouco competitivo"))))
